tftf/__init__.py
tftf/activations/__init__.py
tftf/datasets/Dataset.py
tftf/datasets/__init__.py
tftf/datasets/imdb.py
tftf/datasets/mnist.py
tftf/datasets/small_parallel_enja.py
tftf/initializers/__init__.py
tftf/layers/Activation.py
tftf/layers/Attention.py
tftf/layers/BatchNormalization.py
tftf/layers/Conv2D.py
tftf/layers/Dense.py
tftf/layers/Dropout.py
tftf/layers/Embedding.py
tftf/layers/Flatten.py
tftf/layers/GlobalAveragePooling2D.py
tftf/layers/LSTM.py
tftf/layers/Layer.py
tftf/layers/LayerNormalization.py
tftf/layers/MaxPooling2D.py
tftf/layers/NAC.py
tftf/layers/NALU.py
tftf/layers/PositionalEncoding.py
tftf/layers/RNN.py
tftf/layers/TimeDistributedDense.py
tftf/layers/__init__.py
tftf/layers/activations/__init__.py
tftf/layers/activations/elu.py
tftf/layers/activations/hard_sigmoid.py
tftf/layers/activations/leaky_relu.py
tftf/layers/activations/linear.py
tftf/layers/activations/prelu.py
tftf/layers/activations/relu.py
tftf/layers/activations/selu.py
tftf/layers/activations/sigmoid.py
tftf/layers/activations/softmax.py
tftf/layers/activations/swish.py
tftf/layers/activations/tanh.py
tftf/layers/initializers/__init__.py
tftf/layers/initializers/glorot_normal.py
tftf/layers/initializers/glorot_uniform.py
tftf/layers/initializers/normal.py
tftf/layers/initializers/ones.py
tftf/layers/initializers/orthogonal.py
tftf/layers/initializers/zeros.py
tftf/layers/modules/Module.py
tftf/layers/modules/ResNet.py
tftf/layers/modules/Transformer.py
tftf/layers/modules/__init__.py
tftf/layers/regularizers/__init__.py
tftf/layers/regularizers/l1.py
tftf/layers/regularizers/l1_l2.py
tftf/layers/regularizers/l2.py
tftf/losses/__init__.py
tftf/metrics/__init__.py
tftf/models/Model.py
tftf/models/__init__.py
tftf/models/callbacks/EarlyStopping.py
tftf/models/callbacks/__init__.py
tftf/models/losses/__init__.py
tftf/models/losses/binary_crossentropy.py
tftf/models/losses/categorical_crossentropy.py
tftf-0.0.29.dist-info/DESCRIPTION.rst
tftf-0.0.29.dist-info/METADATA
tftf-0.0.29.dist-info/RECORD
tftf-0.0.29.dist-info/WHEEL
tftf-0.0.29.dist-info/metadata.json
tftf-0.0.29.dist-info/top_level.txt
